pydantic_openapi/__init__.py
pydantic_openapi/camel_case.py
pydantic_openapi/command_line.py
pydantic_openapi/openapi_generator.py
pydantic_openapi-0.1.4.dist-info/entry_points.txt
pydantic_openapi-0.1.4.dist-info/LICENSE
pydantic_openapi-0.1.4.dist-info/WHEEL
pydantic_openapi-0.1.4.dist-info/METADATA
pydantic_openapi-0.1.4.dist-info/RECORD
